ctc_metrics/__init__.py
ctc_metrics/metrics/__init__.py
ctc_metrics/metrics/biological/__init__.py
ctc_metrics/metrics/biological/bc.py
ctc_metrics/metrics/biological/bio.py
ctc_metrics/metrics/biological/cca.py
ctc_metrics/metrics/biological/ct.py
ctc_metrics/metrics/biological/op_clb.py
ctc_metrics/metrics/biological/tf.py
ctc_metrics/metrics/clearmot/__init__.py
ctc_metrics/metrics/clearmot/mota.py
ctc_metrics/metrics/hota/__init__.py
ctc_metrics/metrics/hota/chota.py
ctc_metrics/metrics/hota/hota.py
ctc_metrics/metrics/identity_metrics/__init__.py
ctc_metrics/metrics/identity_metrics/idf1.py
ctc_metrics/metrics/others/__init__.py
ctc_metrics/metrics/others/faf.py
ctc_metrics/metrics/others/mt_ml.py
ctc_metrics/metrics/technical/__init__.py
ctc_metrics/metrics/technical/det.py
ctc_metrics/metrics/technical/lnk.py
ctc_metrics/metrics/technical/op_csb.py
ctc_metrics/metrics/technical/op_ctb.py
ctc_metrics/metrics/technical/seg.py
ctc_metrics/metrics/technical/tra.py
ctc_metrics/metrics/validation/__init__.py
ctc_metrics/metrics/validation/valid.py
ctc_metrics/scripts/__init__.py
ctc_metrics/scripts/evaluate.py
ctc_metrics/scripts/noise.py
ctc_metrics/scripts/validate.py
ctc_metrics/scripts/visualize.py
ctc_metrics/utils/__init__.py
ctc_metrics/utils/filesystem.py
ctc_metrics/utils/handle_results.py
ctc_metrics/utils/representations.py
py_ctcmetrics-1.3.2.dist-info/licenses/LICENSE.txt
test/__init__.py
test/test_metrics.py
test/test_validate.py
test/utils.py
py_ctcmetrics-1.3.2.dist-info/METADATA
py_ctcmetrics-1.3.2.dist-info/WHEEL
py_ctcmetrics-1.3.2.dist-info/entry_points.txt
py_ctcmetrics-1.3.2.dist-info/top_level.txt
py_ctcmetrics-1.3.2.dist-info/RECORD
