Metadata-Version: 2.4
Name: py-ctcmetrics
Version: 1.3.2
Summary: Metrics for Cell Tracking Challenges
Author: Timo Kaiser
Author-email: kaiser@tnt.uni-hannover.de
License-File: LICENSE.txt
Requires-Dist: numpy
Requires-Dist: scikit-learn
Requires-Dist: scipy
Requires-Dist: tifffile
Requires-Dist: imagecodecs
Requires-Dist: pandas
Provides-Extra: viz
Requires-Dist: opencv-python; extra == "viz"
Dynamic: author
Dynamic: author-email
Dynamic: description
Dynamic: license-file
Dynamic: provides-extra
Dynamic: requires-dist
Dynamic: summary
